{
  "$schema": "https://ui.shadcn.com/schema/registry-item.json",
  "name": "theme",
  "type": "registry:theme",
  "title": "Nature Theme",
  "description": "A nature theme and styles with greens and browns using Tailwind and shadcn/ui variable names",
  "files": [
    {
      "path": "src/app/globals.css",
      "content": "@import \"tailwindcss\";\n@import \"tw-animate-css\";\n\n@custom-variant dark (&:is(.dark *));\n\n:root {\n  --background: oklch(1.0 0.0 0.0);\n  --foreground: oklch(0.3 0.04 30.2);\n\n  --card: oklch(1 0 0);\n  --card-foreground: oklch(0.37 0.04 257);\n\n  --popover: oklch(1 0 0);\n  --popover-foreground: oklch(0.37 0.04 257);\n\n  --primary: oklch(0.59 0.20 277);\n  --primary-foreground: oklch(0.96 0.02 272);\n\n  --secondary: oklch(0.98 0.00 248);\n  --secondary-foreground: oklch(0.37 0.04 257);\n\n  --muted: oklch(0.984 0.003 247.858);\n  --muted-foreground: oklch(0.55 0.04 257);\n\n  --accent: oklch(0.96 0.02 272);\n  --accent-foreground: oklch(0.69 0.21 274);\n\n  --destructive: oklch(0.64 0.21 25);\n  --destructive-foreground: oklch(0.97 0.01 17);\n\n  --border: oklch(0.93 0.01 256);\n  --input: oklch(0.93 0.01 256);\n  --ring: oklch(0.93 0.01 256);\n\n  --chart-1: oklch(0.67 0.16 144.21);\n  --chart-2: oklch(0.58 0.14 144.18);\n  --chart-3: oklch(0.52 0.13 144.17);\n  --chart-4: oklch(0.43 0.12 144.31);\n  --chart-5: oklch(0.22 0.05 145.73);\n\n  --sidebar: oklch(1.0 0.0 0.0);\n  --sidebar-foreground: oklch(0.37 0.04 257);\n  --sidebar-primary: oklch(0.37 0.04 257);\n  --sidebar-primary-foreground: oklch(0.99 0.00 0);\n  --sidebar-accent: oklch(0.96 0.02 272);\n  --sidebar-accent-foreground:oklch(0.69 0.21 274);\n  --sidebar-border: oklch(0.93 0.01 256);\n  --sidebar-ring: oklch(0.93 0.01 256);\n\n  --radius: 0.875rem;\n}\n\n.dark {\n  --background: oklch(0.15 0.01 74.42);\n  --foreground: oklch(0.95 0.02 80.72);\n\n  --card: oklch(0.12 0.01 80.72);\n  --card-foreground: oklch(0.95 0.02 80.72);\n\n  --popover: oklch(0.12 0.01 80.72);\n  --popover-foreground: oklch(0.95 0.02 80.72);\n\n  --primary: oklch(0.59 0.20 277);\n  --primary-foreground: oklch(0.96 0.02 272);\n\n  --secondary: oklch(0.15 0.02 147.64);\n  --secondary-foreground: oklch(0.65 0.12 144.31);\n\n  --muted: oklch(0.18 0.01 74.42);\n  --muted-foreground: oklch(0.65 0.03 74.42);\n\n  --accent: oklch(0.22 0.04 146.04);\n  --accent-foreground: oklch(0.65 0.12 144.31);\n\n  --destructive: oklch(0.62 0.22 26.72);\n  --destructive-foreground: oklch(0.95 0.02 80.72);\n\n  --border: oklch(0.22 0.02 74.64);\n  --input: oklch(0.22 0.02 74.64);\n  --ring: oklch(0.58 0.15 144.17);\n\n  --chart-1: oklch(0.72 0.16 144.21);\n  --chart-2: oklch(0.63 0.14 144.18);\n  --chart-3: oklch(0.58 0.15 144.17);\n  --chart-4: oklch(0.48 0.12 144.31);\n  --chart-5: oklch(0.35 0.08 145.73);\n\n  --sidebar: oklch(0.15 0.01 74.42);\n  --sidebar-foreground: oklch(0.95 0.02 80.72);\n  --sidebar-primary: oklch(0.58 0.15 144.17);\n  --sidebar-primary-foreground: oklch(0.09 0.01 80.72);\n  --sidebar-accent: oklch(0.22 0.04 146.04);\n  --sidebar-accent-foreground: oklch(0.65 0.12 144.31);\n  --sidebar-border: oklch(0.22 0.02 74.64);\n  --sidebar-ring: oklch(0.58 0.15 144.17);\n}\n\n@theme inline {\n  --color-background: var(--background);\n  --color-foreground: var(--foreground);\n\n  --color-primary: var(--primary);\n  --color-primary-foreground: var(--primary-foreground);\n\n  --color-secondary: var(--secondary);\n  --color-secondary-foreground: var(--secondary-foreground);\n  --color-accent: var(--accent);\n  --color-accent-foreground: var(--accent-foreground);\n\n  --color-muted: var(--muted);\n  --color-muted-foreground: var(--muted-foreground);\n  --color-card: var(--card);\n  --color-card-foreground: var(--card-foreground);\n  --color-popover: var(--popover);\n  --color-popover-foreground: var(--popover-foreground);\n\n  --color-border: var(--border);\n  --color-input: var(--input);\n  --color-ring: var(--ring);\n\n  --color-destructive: var(--destructive);\n  --color-destructive-foreground: var(--destructive-foreground);\n\n  --color-chart-1: var(--chart-1);\n  --color-chart-2: var(--chart-2);\n  --color-chart-3: var(--chart-3);\n  --color-chart-4: var(--chart-4);\n  --color-chart-5: var(--chart-5);\n\n  --color-sidebar: var(--sidebar);\n  --color-sidebar-foreground: var(--sidebar-foreground);\n  --color-sidebar-primary: var(--sidebar-primary);\n  --color-sidebar-primary-foreground: var(--sidebar-primary-foreground);\n  --color-sidebar-accent: var(--sidebar-accent);\n  --color-sidebar-accent-foreground: var(--sidebar-accent-foreground);\n  --color-sidebar-border: var(--sidebar-border);\n  --color-sidebar-ring: var(--sidebar-ring);\n\n  --font-sans: var(--font-sans);\n  --font-serif: var(--font-serif);\n  --font-mono: var(--font-mono);\n\n  --radius-sm: calc(var(--radius) - 4px);\n  --radius-md: calc(var(--radius) - 2px);\n  --radius-lg: var(--radius);\n  --radius-xl: calc(var(--radius) + 4px);\n\n  --shadow-2xs: var(--shadow-2xs);\n  --shadow-xs: var(--shadow-xs);\n  --shadow-sm: var(--shadow-sm);\n  --shadow: var(--shadow);\n  --shadow-md: var(--shadow-md);\n  --shadow-lg: var(--shadow-lg);\n  --shadow-xl: var(--shadow-xl);\n  --shadow-2xl: var(--shadow-2xl);\n}\n\n@layer base {\n  *,\n  ::after,\n  ::before,\n  ::backdrop,\n  ::file-selector-button {\n    border-color: var(--color-border, currentColor);\n  }\n}\n",
      "type": "registry:style",
      "target": "app/globals.css"
    },
    {
      "path": "postcss.config.mjs",
      "content": "/** @type {import('postcss-load-config').Config} */\nexport default {\n  plugins: {\n    \"@tailwindcss/postcss\": {},\n  },\n};\n",
      "type": "registry:file",
      "target": "postcss.config.mjs"
    }
  ],
  "cssVars": {
    "light": {
      "background": "oklch(1.0 0.0 0.0)",
      "foreground": "oklch(0.3 0.04 30.2)",
      "card": "oklch(1 0 0)",
      "card-foreground": "oklch(0.37 0.04 257)",
      "popover": "oklch(1 0 0)",
      "popover-foreground": "oklch(0.37 0.04 257)",
      "primary": "oklch(0.59 0.20 277)",
      "primary-foreground": "oklch(0.96 0.02 272)",
      "secondary": "oklch(0.98 0.00 248)",
      "secondary-foreground": "oklch(0.37 0.04 257)",
      "muted": "oklch(0.984 0.003 247.858)",
      "muted-foreground": "oklch(0.55 0.04 257)",
      "accent": "oklch(0.96 0.02 272)",
      "accent-foreground": "oklch(0.69 0.21 274)",
      "destructive": "oklch(0.64 0.21 25)",
      "destructive-foreground": "oklch(0.97 0.01 17)",
      "border": "oklch(0.93 0.01 256)",
      "input": "oklch(0.93 0.01 256)",
      "ring": "oklch(0.93 0.01 256)",
      "chart-1": "oklch(0.67 0.16 144.21)",
      "chart-2": "oklch(0.58 0.14 144.18)",
      "chart-3": "oklch(0.52 0.13 144.17)",
      "chart-4": "oklch(0.43 0.12 144.31)",
      "chart-5": "oklch(0.22 0.05 145.73)",
      "sidebar": "oklch(1.0 0.0 0.0)",
      "sidebar-foreground": "oklch(0.37 0.04 257)",
      "sidebar-primary": "oklch(0.37 0.04 257)",
      "sidebar-primary-foreground": "oklch(0.99 0.00 0)",
      "sidebar-accent": "oklch(0.96 0.02 272)",
      "sidebar-accent-foreground": "oklch(0.69 0.21 274)",
      "sidebar-border": "oklch(0.93 0.01 256)",
      "sidebar-ring": "oklch(0.93 0.01 256)",
      "radius": "0.875rem"
    },
    "dark": {
      "background": "oklch(0.15 0.01 74.42)",
      "foreground": "oklch(0.95 0.02 80.72)",
      "card": "oklch(0.12 0.01 80.72)",
      "card-foreground": "oklch(0.95 0.02 80.72)",
      "popover": "oklch(0.12 0.01 80.72)",
      "popover-foreground": "oklch(0.95 0.02 80.72)",
      "primary": "oklch(0.59 0.20 277)",
      "primary-foreground": "oklch(0.96 0.02 272)",
      "secondary": "oklch(0.15 0.02 147.64)",
      "secondary-foreground": "oklch(0.65 0.12 144.31)",
      "muted": "oklch(0.18 0.01 74.42)",
      "muted-foreground": "oklch(0.65 0.03 74.42)",
      "accent": "oklch(0.22 0.04 146.04)",
      "accent-foreground": "oklch(0.65 0.12 144.31)",
      "destructive": "oklch(0.62 0.22 26.72)",
      "destructive-foreground": "oklch(0.95 0.02 80.72)",
      "border": "oklch(0.22 0.02 74.64)",
      "input": "oklch(0.22 0.02 74.64)",
      "ring": "oklch(0.58 0.15 144.17)",
      "chart-1": "oklch(0.72 0.16 144.21)",
      "chart-2": "oklch(0.63 0.14 144.18)",
      "chart-3": "oklch(0.58 0.15 144.17)",
      "chart-4": "oklch(0.48 0.12 144.31)",
      "chart-5": "oklch(0.35 0.08 145.73)",
      "sidebar": "oklch(0.15 0.01 74.42)",
      "sidebar-foreground": "oklch(0.95 0.02 80.72)",
      "sidebar-primary": "oklch(0.58 0.15 144.17)",
      "sidebar-primary-foreground": "oklch(0.09 0.01 80.72)",
      "sidebar-accent": "oklch(0.22 0.04 146.04)",
      "sidebar-accent-foreground": "oklch(0.65 0.12 144.31)",
      "sidebar-border": "oklch(0.22 0.02 74.64)",
      "sidebar-ring": "oklch(0.58 0.15 144.17)"
    }
  }
}